wolfsoftware/pypi_extractor/__init__.py
wolfsoftware/pypi_extractor/exceptions.py
wolfsoftware/pypi_extractor/pypi.py
wolfsoftware.pypi_extractor-0.1.3.dist-info/LICENSE.md
wolfsoftware.pypi_extractor-0.1.3.dist-info/METADATA
wolfsoftware.pypi_extractor-0.1.3.dist-info/WHEEL
wolfsoftware.pypi_extractor-0.1.3.dist-info/top_level.txt
wolfsoftware.pypi_extractor-0.1.3.dist-info/RECORD
