Metadata-Version: 2.1
Name: wolfsoftware.pypi-extractor
Version: 0.1.3
Summary: Extract package information for a given user in PyPi.
Home-page: https://github.com/DevelopersToolbox/pypi-extractor-package
Author: Wolf Software
Author-email: pypi@wolfsoftware.com
License: MIT
Project-URL:  Source, https://github.com/DevelopersToolbox/pypi-extractor-package
Project-URL:  Tracker, https://github.com/wDevelopersToolbox/pypi-extractor-package/issues/
Project-URL:  Documentation, https://github.com/DevelopersToolbox/pypi-extractor-package
Project-URL:  Sponsor, https://github.com/sponsors/WolfSoftware
Keywords: python,pypi
Classifier: Development Status :: 4 - Beta
Classifier: Environment :: Console
Classifier: Intended Audience :: Developers
Classifier: License :: OSI Approved :: MIT License
Classifier: Programming Language :: Python :: 3
Classifier: Programming Language :: Python :: 3.9
Classifier: Programming Language :: Python :: 3.10
Classifier: Programming Language :: Python :: 3.11
Classifier: Programming Language :: Python :: 3.12
Classifier: Operating System :: OS Independent
Classifier: Topic :: Software Development
Requires-Python: >=3.9
License-File: LICENSE.md
Requires-Dist: requests==2.32.3
Requires-Dist: beautifulsoup4==4.12.3
Requires-Dist: playwright==1.49.1
